{
  "total_sorteos": 2448,
  "frequencies": {
    "1": {
      "count": 1374,
      "pct": 56.13
    },
    "2": {
      "count": 1347,
      "pct": 55.02
    },
    "3": {
      "count": 1366,
      "pct": 55.8
    },
    "4": {
      "count": 1409,
      "pct": 57.56
    },
    "5": {
      "count": 1426,
      "pct": 58.25
    },
    "6": {
      "count": 1383,
      "pct": 56.5
    },
    "7": {
      "count": 1357,
      "pct": 55.43
    },
    "8": {
      "count": 1400,
      "pct": 57.19
    },
    "9": {
      "count": 1399,
      "pct": 57.15
    },
    "10": {
      "count": 1443,
      "pct": 58.95
    },
    "11": {
      "count": 1348,
      "pct": 55.07
    },
    "12": {
      "count": 1389,
      "pct": 56.74
    },
    "13": {
      "count": 1378,
      "pct": 56.29
    },
    "14": {
      "count": 1335,
      "pct": 54.53
    },
    "15": {
      "count": 1380,
      "pct": 56.37
    },
    "16": {
      "count": 1359,
      "pct": 55.51
    },
    "17": {
      "count": 1347,
      "pct": 55.02
    },
    "18": {
      "count": 1346,
      "pct": 54.98
    },
    "19": {
      "count": 1354,
      "pct": 55.31
    },
    "20": {
      "count": 1336,
      "pct": 54.58
    },
    "21": {
      "count": 1364,
      "pct": 55.72
    },
    "22": {
      "count": 1343,
      "pct": 54.86
    },
    "23": {
      "count": 1345,
      "pct": 54.94
    },
    "24": {
      "count": 1362,
      "pct": 55.64
    },
    "25": {
      "count": 1382,
      "pct": 56.45
    }
  },
  "gaps": {
    "1": 0,
    "2": 3,
    "3": 0,
    "4": 0,
    "5": 1,
    "6": 0,
    "7": 0,
    "8": 1,
    "9": 0,
    "10": 1,
    "11": 2,
    "12": 3,
    "13": 6,
    "14": 2,
    "15": 1,
    "16": 0,
    "17": 0,
    "18": 0,
    "19": 4,
    "20": 0,
    "21": 0,
    "22": 0,
    "23": 0,
    "24": 0,
    "25": 1
  },
  "sum_stats": {
    "min": 117,
    "max": 239,
    "mean": 181.1,
    "p10": 157,
    "p25": 169,
    "p75": 194,
    "p90": 205
  },
  "pares_pct": 48.0,
  "top_pairs": [
    {
      "pair": "5-10",
      "count": 821
    },
    {
      "pair": "8-10",
      "count": 814
    },
    {
      "pair": "9-10",
      "count": 811
    },
    {
      "pair": "4-10",
      "count": 804
    },
    {
      "pair": "10-12",
      "count": 802
    },
    {
      "pair": "6-10",
      "count": 796
    },
    {
      "pair": "5-13",
      "count": 796
    },
    {
      "pair": "5-25",
      "count": 794
    },
    {
      "pair": "4-5",
      "count": 792
    },
    {
      "pair": "5-9",
      "count": 792
    }
  ],
  "ultimo_sorteo": {
    "sorteo": 3246,
    "fecha": "2026-06-28",
    "dia": "Sunday",
    "numeros": [
      1,
      3,
      4,
      6,
      7,
      9,
      16,
      17,
      18,
      20,
      21,
      22,
      23,
      24
    ]
  },
  "suggestions": {
    "50": [
      {
        "combo": [
          2,
          3,
          5,
          7,
          8,
          11,
          12,
          14,
          17,
          18,
          20,
          21,
          24,
          25
        ],
        "suma": 187,
        "score": 1.0,
        "popularidad": 0.0,
        "mean_gap": 1.77,
        "gap_std": 0.8,
        "zones": [
          3,
          4,
          3,
          4
        ],
        "parity": [
          7,
          7
        ]
      },
      {
        "combo": [
          1,
          3,
          4,
          6,
          9,
          10,
          12,
          13,
          15,
          16,
          19,
          21,
          23,
          25
        ],
        "suma": 177,
        "score": 0.978,
        "popularidad": 0.0,
        "mean_gap": 1.85,
        "gap_std": 0.66,
        "zones": [
          4,
          3,
          3,
          4
        ],
        "parity": [
          5,
          9
        ]
      },
      {
        "combo": [
          1,
          2,
          4,
          5,
          8,
          9,
          11,
          13,
          14,
          16,
          17,
          19,
          22,
          25
        ],
        "suma": 166,
        "score": 1.0,
        "popularidad": 0.0,
        "mean_gap": 1.85,
        "gap_std": 0.77,
        "zones": [
          4,
          3,
          4,
          3
        ],
        "parity": [
          6,
          8
        ]
      }
    ],
    "100": [
      {
        "combo": [
          1,
          2,
          6,
          7,
          10,
          13,
          14,
          16,
          17,
          19,
          21,
          22,
          24,
          25
        ],
        "suma": 197,
        "score": 1.0,
        "popularidad": 0.0,
        "mean_gap": 1.85,
        "gap_std": 0.95,
        "zones": [
          3,
          2,
          4,
          5
        ],
        "parity": [
          7,
          7
        ]
      },
      {
        "combo": [
          2,
          3,
          4,
          5,
          8,
          9,
          11,
          12,
          14,
          15,
          16,
          18,
          22,
          23
        ],
        "suma": 162,
        "score": 0.925,
        "popularidad": 0.1,
        "mean_gap": 1.62,
        "gap_std": 0.92,
        "zones": [
          4,
          4,
          4,
          2
        ],
        "parity": [
          8,
          6
        ]
      },
      {
        "combo": [
          4,
          5,
          7,
          8,
          10,
          11,
          13,
          14,
          17,
          18,
          20,
          21,
          23,
          25
        ],
        "suma": 196,
        "score": 0.995,
        "popularidad": 0.0,
        "mean_gap": 1.62,
        "gap_std": 0.62,
        "zones": [
          2,
          4,
          4,
          4
        ],
        "parity": [
          6,
          8
        ]
      }
    ],
    "250": [
      {
        "combo": [
          2,
          4,
          5,
          7,
          8,
          13,
          14,
          16,
          17,
          19,
          20,
          22,
          23,
          25
        ],
        "suma": 195,
        "score": 1.0,
        "popularidad": 0.0,
        "mean_gap": 1.77,
        "gap_std": 1.05,
        "zones": [
          3,
          2,
          4,
          5
        ],
        "parity": [
          7,
          7
        ]
      },
      {
        "combo": [
          1,
          3,
          4,
          6,
          8,
          10,
          12,
          15,
          16,
          18,
          19,
          21,
          23,
          24
        ],
        "suma": 180,
        "score": 0.993,
        "popularidad": 0.0,
        "mean_gap": 1.77,
        "gap_std": 0.58,
        "zones": [
          4,
          3,
          3,
          4
        ],
        "parity": [
          8,
          6
        ]
      },
      {
        "combo": [
          2,
          3,
          5,
          6,
          9,
          11,
          12,
          15,
          17,
          19,
          20,
          22,
          24,
          25
        ],
        "suma": 190,
        "score": 0.999,
        "popularidad": 0.0,
        "mean_gap": 1.77,
        "gap_std": 0.7,
        "zones": [
          4,
          3,
          2,
          5
        ],
        "parity": [
          6,
          8
        ]
      }
    ],
    "500": [
      {
        "combo": [
          1,
          4,
          6,
          7,
          10,
          12,
          13,
          16,
          17,
          19,
          20,
          22,
          23,
          25
        ],
        "suma": 195,
        "score": 1.0,
        "popularidad": 0.0,
        "mean_gap": 1.85,
        "gap_std": 0.77,
        "zones": [
          3,
          3,
          3,
          5
        ],
        "parity": [
          7,
          7
        ]
      },
      {
        "combo": [
          1,
          2,
          5,
          8,
          9,
          11,
          12,
          14,
          15,
          17,
          18,
          21,
          24,
          25
        ],
        "suma": 182,
        "score": 1.0,
        "popularidad": 0.0,
        "mean_gap": 1.85,
        "gap_std": 0.86,
        "zones": [
          3,
          4,
          4,
          3
        ],
        "parity": [
          6,
          8
        ]
      },
      {
        "combo": [
          3,
          4,
          6,
          8,
          10,
          11,
          13,
          15,
          18,
          19,
          21,
          22,
          24,
          25
        ],
        "suma": 199,
        "score": 0.994,
        "popularidad": 0.0,
        "mean_gap": 1.69,
        "gap_std": 0.61,
        "zones": [
          3,
          3,
          3,
          5
        ],
        "parity": [
          7,
          7
        ]
      }
    ],
    "1000": [
      {
        "combo": [
          1,
          2,
          6,
          8,
          9,
          11,
          13,
          14,
          16,
          18,
          21,
          22,
          24,
          25
        ],
        "suma": 190,
        "score": 1.0,
        "popularidad": 0.0,
        "mean_gap": 1.85,
        "gap_std": 0.86,
        "zones": [
          3,
          3,
          4,
          4
        ],
        "parity": [
          8,
          6
        ]
      },
      {
        "combo": [
          3,
          4,
          7,
          10,
          11,
          12,
          15,
          16,
          17,
          19,
          20,
          21,
          23,
          24
        ],
        "suma": 202,
        "score": 0.925,
        "popularidad": 0.1,
        "mean_gap": 1.62,
        "gap_std": 0.84,
        "zones": [
          2,
          4,
          3,
          5
        ],
        "parity": [
          6,
          8
        ]
      },
      {
        "combo": [
          2,
          3,
          5,
          6,
          8,
          9,
          12,
          13,
          17,
          19,
          20,
          22,
          23,
          25
        ],
        "suma": 184,
        "score": 1.0,
        "popularidad": 0.0,
        "mean_gap": 1.77,
        "gap_std": 0.89,
        "zones": [
          4,
          3,
          2,
          5
        ],
        "parity": [
          6,
          8
        ]
      }
    ],
    "all": [
      {
        "combo": [
          1,
          2,
          5,
          6,
          9,
          10,
          12,
          13,
          15,
          16,
          18,
          20,
          23,
          24
        ],
        "suma": 174,
        "score": 1.0,
        "popularidad": 0.0,
        "mean_gap": 1.77,
        "gap_std": 0.8,
        "zones": [
          4,
          3,
          4,
          3
        ],
        "parity": [
          8,
          6
        ]
      },
      {
        "combo": [
          2,
          4,
          7,
          8,
          10,
          11,
          13,
          14,
          17,
          19,
          21,
          22,
          24,
          25
        ],
        "suma": 197,
        "score": 0.999,
        "popularidad": 0.0,
        "mean_gap": 1.77,
        "gap_std": 0.7,
        "zones": [
          2,
          4,
          3,
          5
        ],
        "parity": [
          7,
          7
        ]
      },
      {
        "combo": [
          1,
          3,
          5,
          6,
          8,
          9,
          11,
          12,
          14,
          15,
          17,
          21,
          24,
          25
        ],
        "suma": 171,
        "score": 0.981,
        "popularidad": 0.0,
        "mean_gap": 1.85,
        "gap_std": 0.86,
        "zones": [
          4,
          4,
          3,
          3
        ],
        "parity": [
          5,
          9
        ]
      }
    ],
    "dia": [
      {
        "combo": [
          1,
          2,
          5,
          7,
          8,
          10,
          13,
          16,
          18,
          19,
          21,
          22,
          24,
          25
        ],
        "suma": 191,
        "score": 1.0,
        "popularidad": 0.0,
        "mean_gap": 1.85,
        "gap_std": 0.77,
        "zones": [
          3,
          3,
          3,
          5
        ],
        "parity": [
          7,
          7
        ]
      },
      {
        "combo": [
          2,
          3,
          4,
          6,
          8,
          9,
          10,
          11,
          12,
          14,
          17,
          20,
          23,
          25
        ],
        "suma": 164,
        "score": 0.925,
        "popularidad": 0.1,
        "mean_gap": 1.77,
        "gap_std": 0.8,
        "zones": [
          4,
          5,
          2,
          3
        ],
        "parity": [
          8,
          6
        ]
      },
      {
        "combo": [
          1,
          4,
          6,
          7,
          10,
          12,
          13,
          15,
          17,
          18,
          20,
          21,
          23,
          24
        ],
        "suma": 191,
        "score": 0.999,
        "popularidad": 0.0,
        "mean_gap": 1.77,
        "gap_std": 0.7,
        "zones": [
          3,
          3,
          4,
          4
        ],
        "parity": [
          7,
          7
        ]
      }
    ],
    "mes": [
      {
        "combo": [
          1,
          3,
          4,
          7,
          8,
          11,
          12,
          16,
          18,
          19,
          21,
          22,
          24,
          25
        ],
        "suma": 191,
        "score": 1.0,
        "popularidad": 0.0,
        "mean_gap": 1.85,
        "gap_std": 0.95,
        "zones": [
          3,
          4,
          2,
          5
        ],
        "parity": [
          7,
          7
        ]
      },
      {
        "combo": [
          1,
          2,
          3,
          5,
          6,
          7,
          9,
          10,
          13,
          17,
          20,
          22,
          23,
          24
        ],
        "suma": 162,
        "score": 0.925,
        "popularidad": 0.1,
        "mean_gap": 1.77,
        "gap_std": 0.97,
        "zones": [
          5,
          3,
          2,
          4
        ],
        "parity": [
          6,
          8
        ]
      },
      {
        "combo": [
          1,
          2,
          5,
          6,
          8,
          11,
          14,
          15,
          17,
          18,
          20,
          21,
          24,
          25
        ],
        "suma": 187,
        "score": 1.0,
        "popularidad": 0.0,
        "mean_gap": 1.85,
        "gap_std": 0.86,
        "zones": [
          4,
          2,
          4,
          4
        ],
        "parity": [
          7,
          7
        ]
      }
    ]
  },
  "rekino": {
    "total_sorteos": 2383,
    "frequencies": {
      "1": {
        "count": 1310,
        "pct": 54.97
      },
      "2": {
        "count": 1352,
        "pct": 56.74
      },
      "3": {
        "count": 1338,
        "pct": 56.15
      },
      "4": {
        "count": 1354,
        "pct": 56.82
      },
      "5": {
        "count": 1362,
        "pct": 57.15
      },
      "6": {
        "count": 1345,
        "pct": 56.44
      },
      "7": {
        "count": 1343,
        "pct": 56.36
      },
      "8": {
        "count": 1305,
        "pct": 54.76
      },
      "9": {
        "count": 1292,
        "pct": 54.22
      },
      "10": {
        "count": 1353,
        "pct": 56.78
      },
      "11": {
        "count": 1315,
        "pct": 55.18
      },
      "12": {
        "count": 1357,
        "pct": 56.95
      },
      "13": {
        "count": 1335,
        "pct": 56.02
      },
      "14": {
        "count": 1332,
        "pct": 55.9
      },
      "15": {
        "count": 1367,
        "pct": 57.36
      },
      "16": {
        "count": 1351,
        "pct": 56.69
      },
      "17": {
        "count": 1317,
        "pct": 55.27
      },
      "18": {
        "count": 1319,
        "pct": 55.35
      },
      "19": {
        "count": 1331,
        "pct": 55.85
      },
      "20": {
        "count": 1339,
        "pct": 56.19
      },
      "21": {
        "count": 1293,
        "pct": 54.26
      },
      "22": {
        "count": 1350,
        "pct": 56.65
      },
      "23": {
        "count": 1327,
        "pct": 55.69
      },
      "24": {
        "count": 1324,
        "pct": 55.56
      },
      "25": {
        "count": 1351,
        "pct": 56.69
      }
    },
    "gaps": {
      "1": 0,
      "2": 1,
      "3": 0,
      "4": 1,
      "5": 0,
      "6": 0,
      "7": 0,
      "8": 0,
      "9": 7,
      "10": 0,
      "11": 0,
      "12": 2,
      "13": 0,
      "14": 1,
      "15": 1,
      "16": 1,
      "17": 1,
      "18": 0,
      "19": 0,
      "20": 1,
      "21": 1,
      "22": 0,
      "23": 5,
      "24": 0,
      "25": 0
    },
    "sum_stats": {
      "min": 129,
      "max": 259,
      "mean": 181.8,
      "p10": 158,
      "p25": 170,
      "p75": 194,
      "p90": 205
    },
    "pares_pct": 48.2,
    "top_pairs": [
      {
        "pair": "12-15",
        "count": 778
      },
      {
        "pair": "5-13",
        "count": 777
      },
      {
        "pair": "4-5",
        "count": 768
      },
      {
        "pair": "3-15",
        "count": 767
      },
      {
        "pair": "15-25",
        "count": 766
      },
      {
        "pair": "5-12",
        "count": 765
      },
      {
        "pair": "5-15",
        "count": 764
      },
      {
        "pair": "10-12",
        "count": 764
      },
      {
        "pair": "5-16",
        "count": 760
      },
      {
        "pair": "16-25",
        "count": 759
      }
    ],
    "ultimo_sorteo": {
      "sorteo": 3245,
      "fecha": "2026-06-26",
      "dia": "Friday",
      "numeros": [
        1,
        3,
        5,
        6,
        7,
        8,
        10,
        11,
        13,
        18,
        19,
        22,
        24,
        25
      ]
    }
  },
  "requetekino": {
    "total_sorteos": 353,
    "frequencies": {
      "1": {
        "count": 198,
        "pct": 56.09
      },
      "2": {
        "count": 189,
        "pct": 53.54
      },
      "3": {
        "count": 196,
        "pct": 55.52
      },
      "4": {
        "count": 189,
        "pct": 53.54
      },
      "5": {
        "count": 191,
        "pct": 54.11
      },
      "6": {
        "count": 196,
        "pct": 55.52
      },
      "7": {
        "count": 177,
        "pct": 50.14
      },
      "8": {
        "count": 209,
        "pct": 59.21
      },
      "9": {
        "count": 201,
        "pct": 56.94
      },
      "10": {
        "count": 212,
        "pct": 60.06
      },
      "11": {
        "count": 176,
        "pct": 49.86
      },
      "12": {
        "count": 195,
        "pct": 55.24
      },
      "13": {
        "count": 215,
        "pct": 60.91
      },
      "14": {
        "count": 202,
        "pct": 57.22
      },
      "15": {
        "count": 206,
        "pct": 58.36
      },
      "16": {
        "count": 189,
        "pct": 53.54
      },
      "17": {
        "count": 207,
        "pct": 58.64
      },
      "18": {
        "count": 199,
        "pct": 56.37
      },
      "19": {
        "count": 208,
        "pct": 58.92
      },
      "20": {
        "count": 205,
        "pct": 58.07
      },
      "21": {
        "count": 192,
        "pct": 54.39
      },
      "22": {
        "count": 184,
        "pct": 52.12
      },
      "23": {
        "count": 197,
        "pct": 55.81
      },
      "24": {
        "count": 203,
        "pct": 57.51
      },
      "25": {
        "count": 206,
        "pct": 58.36
      }
    },
    "gaps": {
      "1": 3,
      "2": 2,
      "3": 1,
      "4": 0,
      "5": 1,
      "6": 0,
      "7": 0,
      "8": 0,
      "9": 0,
      "10": 4,
      "11": 2,
      "12": 0,
      "13": 0,
      "14": 0,
      "15": 0,
      "16": 1,
      "17": 0,
      "18": 3,
      "19": 1,
      "20": 0,
      "21": 0,
      "22": 2,
      "23": 1,
      "24": 0,
      "25": 0
    },
    "sum_stats": {
      "min": 139,
      "max": 236,
      "mean": 183.3,
      "p10": 160,
      "p25": 172,
      "p75": 194,
      "p90": 206
    },
    "pares_pct": 48.0,
    "top_pairs": [
      {
        "pair": "13-20",
        "count": 136
      },
      {
        "pair": "13-25",
        "count": 130
      },
      {
        "pair": "10-13",
        "count": 128
      },
      {
        "pair": "13-19",
        "count": 127
      },
      {
        "pair": "10-25",
        "count": 125
      },
      {
        "pair": "10-23",
        "count": 125
      },
      {
        "pair": "9-15",
        "count": 123
      },
      {
        "pair": "13-24",
        "count": 123
      },
      {
        "pair": "1-13",
        "count": 123
      },
      {
        "pair": "9-17",
        "count": 122
      }
    ],
    "ultimo_sorteo": {
      "sorteo": 3245,
      "fecha": "2026-06-26",
      "dia": "Friday",
      "numeros": [
        4,
        6,
        7,
        8,
        9,
        12,
        13,
        14,
        15,
        17,
        20,
        21,
        24,
        25
      ]
    }
  },
  "range_scores": {
    "100": {
      "sorteos_evaluados": 16,
      "aciertos_avg": 7.85,
      "aciertos_max": 12
    },
    "1000": {
      "sorteos_evaluados": 16,
      "aciertos_avg": 7.86,
      "aciertos_max": 12
    },
    "250": {
      "sorteos_evaluados": 16,
      "aciertos_avg": 7.83,
      "aciertos_max": 12
    },
    "50": {
      "sorteos_evaluados": 16,
      "aciertos_avg": 7.83,
      "aciertos_max": 12
    },
    "500": {
      "sorteos_evaluados": 16,
      "aciertos_avg": 7.87,
      "aciertos_max": 12
    },
    "all": {
      "sorteos_evaluados": 16,
      "aciertos_avg": 7.85,
      "aciertos_max": 12
    },
    "dia": {
      "sorteos_evaluados": 2,
      "aciertos_avg": 7.81,
      "aciertos_max": 13
    },
    "mes": {
      "sorteos_evaluados": 2,
      "aciertos_avg": 7.91,
      "aciertos_max": 12
    }
  },
  "premio_mayor_real": {
    "disponible": true,
    "monto": 5656088487,
    "sorteo": 3245,
    "fecha": "2026-06-26",
    "ganadores": 0,
    "categoria": "14 aciertos",
    "fuente": "kino_premios_historial.csv"
  }
}